torchsparsegradutils/__init__.py
torchsparsegradutils/indexed_matmul.py
torchsparsegradutils/sparse_lstsq.py
torchsparsegradutils/sparse_matmul.py
torchsparsegradutils/sparse_solve.py
torchsparsegradutils/benchmarks/__init__.py
torchsparsegradutils/benchmarks/batched_sparse_mm_rand.py
torchsparsegradutils/benchmarks/benchmark_suite.py
torchsparsegradutils/benchmarks/benchmark_utils.py
torchsparsegradutils/benchmarks/sparse_generic_solve_rand.py
torchsparsegradutils/benchmarks/sparse_generic_solve_suite.py
torchsparsegradutils/benchmarks/sparse_mm_rand.py
torchsparsegradutils/benchmarks/sparse_mm_suite.py
torchsparsegradutils/benchmarks/sparse_triangular_solve_rand.py
torchsparsegradutils/benchmarks/sparse_triangular_solve_suitesparse.py
torchsparsegradutils/benchmarks/visualize_benchmark_results.py
torchsparsegradutils/cupy/__init__.py
torchsparsegradutils/cupy/cupy_bindings.py
torchsparsegradutils/cupy/cupy_sparse_solve.py
torchsparsegradutils/distributions/__init__.py
torchsparsegradutils/distributions/constraints.py
torchsparsegradutils/distributions/sparse_multivariate_normal.py
torchsparsegradutils/encoders/__init__.py
torchsparsegradutils/encoders/pairwise_encoder.py
torchsparsegradutils/encoders/pairwise_voxel_encoder.py
torchsparsegradutils/jax/__init__.py
torchsparsegradutils/jax/jax_bindings.py
torchsparsegradutils/jax/jax_sparse_solve.py
torchsparsegradutils/tests/__init__.py
torchsparsegradutils/tests/test_bicgstab.py
torchsparsegradutils/tests/test_cupy_bindings.py
torchsparsegradutils/tests/test_cupy_sparse_solve.py
torchsparsegradutils/tests/test_dist_stats_helpers.py
torchsparsegradutils/tests/test_distributions.py
torchsparsegradutils/tests/test_doctests.py
torchsparsegradutils/tests/test_encoders.py
torchsparsegradutils/tests/test_indexed_matmul.py
torchsparsegradutils/tests/test_integration_pairwise_sparse_mvn.py
torchsparsegradutils/tests/test_jax_bindings.py
torchsparsegradutils/tests/test_jax_sparse_solve.py
torchsparsegradutils-0.2.0.dist-info/licenses/LICENSE
torchsparsegradutils-0.2.0.dist-info/METADATA
torchsparsegradutils-0.2.0.dist-info/WHEEL
torchsparsegradutils-0.2.0.dist-info/top_level.txt
torchsparsegradutils-0.2.0.dist-info/RECORD
