Metadata-Version: 2.4
Name: torchsparsegradutils
Version: 0.2.0
Summary: A collection of utility functions to work with PyTorch sparse tensors
Home-page: https://github.com/cai4cai/torchsparsegradutils
Author: CAI4CAI research group
Author-email: contact@cai4cai.uk
License: Apache-2.0
Keywords: sparse torch utility
Classifier: Operating System :: OS Independent
Classifier: License :: OSI Approved :: Apache Software License
Classifier: Programming Language :: Python :: 3.10
Classifier: Programming Language :: Python :: 3.11
Classifier: Programming Language :: Python :: 3.12
Requires-Python: >=3.10
License-File: LICENSE
Requires-Dist: torch>=2.5
Requires-Dist: scipy
Provides-Extra: extras
Requires-Dist: jax; extra == "extras"
Requires-Dist: cupy; extra == "extras"
Provides-Extra: docs
Requires-Dist: sphinx>=7.0.0; extra == "docs"
Requires-Dist: sphinx-rtd-theme>=1.3.0; extra == "docs"
Requires-Dist: sphinx-copybutton>=0.5.0; extra == "docs"
Requires-Dist: myst-parser>=2.0.0; extra == "docs"
Requires-Dist: sphinx-autobuild>=2021.3.14; extra == "docs"
Requires-Dist: matplotlib>=3.5.0; extra == "docs"
Requires-Dist: sphinx-autodoc-typehints>=1.24.0; extra == "docs"
Dynamic: author
Dynamic: author-email
Dynamic: classifier
Dynamic: description
Dynamic: description-content-type
Dynamic: home-page
Dynamic: keywords
Dynamic: license
Dynamic: license-file
Dynamic: provides-extra
Dynamic: requires-dist
Dynamic: requires-python
Dynamic: summary
